printo/__init__.py
printo/descript.py
printo/filters.py
printo/py.typed
printo/reprs.py
printo-0.0.8.dist-info/LICENSE
printo-0.0.8.dist-info/METADATA
printo-0.0.8.dist-info/WHEEL
printo-0.0.8.dist-info/top_level.txt
printo-0.0.8.dist-info/RECORD
